odoo/addons/base_sparse_field_list_support/README.rst
odoo/addons/base_sparse_field_list_support/__init__.py
odoo/addons/base_sparse_field_list_support/__manifest__.py
odoo/addons/base_sparse_field_list_support/i18n/base_sparse_field_list_support.pot
odoo/addons/base_sparse_field_list_support/models/__init__.py
odoo/addons/base_sparse_field_list_support/models/fields.py
odoo/addons/base_sparse_field_list_support/readme/CONTRIBUTORS.rst
odoo/addons/base_sparse_field_list_support/readme/DESCRIPTION.rst
odoo/addons/base_sparse_field_list_support/static/description/icon.png
odoo/addons/base_sparse_field_list_support/static/description/index.html
odoo13_addon_base_sparse_field_list_support-13.0.1.0.2.dist-info/METADATA
odoo13_addon_base_sparse_field_list_support-13.0.1.0.2.dist-info/WHEEL
odoo13_addon_base_sparse_field_list_support-13.0.1.0.2.dist-info/top_level.txt
odoo13_addon_base_sparse_field_list_support-13.0.1.0.2.dist-info/RECORD
